more_function/__init__.py
more_function/ascending.py
more_function/descending.py
more_function/quadratic.py
more_function-0.1.0.dist-info/licenses/LICENSE
more_function-0.1.0.dist-info/METADATA
more_function-0.1.0.dist-info/WHEEL
more_function-0.1.0.dist-info/top_level.txt
more_function-0.1.0.dist-info/RECORD
