Metadata-Version: 2.4
Name: more_function
Version: 0.1.0
Summary: A small Python library with quadratic solver and sorting functions
Author-email: Dang Minh Tai <dmt826321@gmail.com>
License: MIT
Keywords: math,sorting,quadratic
Requires-Python: >=3.7
License-File: LICENSE
Dynamic: license-file
